README.rst
setup.py
talkey/__init__.py
talkey/base.py
talkey/test_suite.py
talkey/tts.py
talkey/utils.py
talkey.egg-info/PKG-INFO
talkey.egg-info/SOURCES.txt
talkey.egg-info/dependency_links.txt
talkey.egg-info/not-zip-safe
talkey.egg-info/requires.txt
talkey.egg-info/top_level.txt
talkey/engines/__init__.py
talkey/engines/dummy.py
talkey/engines/espeak.py
talkey/engines/festival.py
talkey/engines/flite.py
talkey/engines/google.py
talkey/engines/mary.py
talkey/engines/pico.py